vdl_tools/__init__.py
vdl_tools/temp_run.py
vdl_tools/download_process_images/README.md
vdl_tools/download_process_images/__init__.py
vdl_tools/download_process_images/imagetools.py
vdl_tools/download_process_images/test.py
vdl_tools/download_process_images/test_df.py
vdl_tools/download_process_images/tests/__init__.py
vdl_tools/linkedin/__init__.py
vdl_tools/linkedin/cache.py
vdl_tools/linkedin/configuration.py
vdl_tools/linkedin/org.py
vdl_tools/linkedin/org_loader.py
vdl_tools/linkedin/profile_loader.py
vdl_tools/linkedin/profile_loader_psql.py
vdl_tools/linkedin/experimental/search_and_merge_li.py
vdl_tools/linkedin/handlers/__init__.py
vdl_tools/linkedin/handlers/base_handler.py
vdl_tools/linkedin/handlers/coresignal_bulk.py
vdl_tools/linkedin/handlers/coresignal_query.py
vdl_tools/linkedin/handlers/direct_query.py
vdl_tools/linkedin/processors/__init__.py
vdl_tools/linkedin/processors/coresignal_processor.py
vdl_tools/linkedin/processors/processor_utils.py
vdl_tools/linkedin/processors/profile_cleaning.py
vdl_tools/linkedin/processors/raw_org_processor.py
vdl_tools/linkedin/processors/raw_profile_processor.py
vdl_tools/linkedin/utils/__init__.py
vdl_tools/linkedin/utils/linkedin_url.py
vdl_tools/linkedin/utils/shared.py
vdl_tools/network_tools/__init__.py
vdl_tools/network_tools/bipartite_network_mapping.py
vdl_tools/network_tools/causal_network_metrics.py
vdl_tools/network_tools/network_functions.py
vdl_tools/network_tools/node_similarity.py
vdl_tools/network_tools/optimize_clusters.py
vdl_tools/network_tools/post_build_analysis.py
vdl_tools/network_tools/trophiclevel.py
vdl_tools/notebooks/attention_index.py
vdl_tools/notebooks/attention_index_walkthrough.py
vdl_tools/notebooks/few_shot_tutorial.py
vdl_tools/notebooks/scraped_pages_exploration.py
vdl_tools/notebooks/scratch_attention_index.py
vdl_tools/py2mappr/.gitignore
vdl_tools/py2mappr/README.md
vdl_tools/py2mappr/__init__.py
vdl_tools/py2mappr/_project_manager.py
vdl_tools/py2mappr/map.py
vdl_tools-2.0.1.dist-info/METADATA
vdl_tools-2.0.1.dist-info/WHEEL
vdl_tools-2.0.1.dist-info/RECORD
