Metadata-Version: 2.4
Name: vdl-tools
Version: 2.0.1
Summary: VDL Tools
Author: Vibrant Data Labs
Classifier: Development Status :: 4 - Beta
Classifier: Programming Language :: Python :: 3.12
Requires-Python: <3.13,>=3.12
Requires-Dist: alembic<2.0.0,>=1.13.0
Requires-Dist: altair
Requires-Dist: awscli
Requires-Dist: beautifulsoup4<5.0.0,>=4.14.0
Requires-Dist: bokeh
Requires-Dist: boto3>=1.34.0
Requires-Dist: cairosvg
Requires-Dist: circlify
Requires-Dist: dataclasses-json
Requires-Dist: datasets
Requires-Dist: geopy
Requires-Dist: geotext
Requires-Dist: gitpython
Requires-Dist: google-api-python-client>=2.100.0
Requires-Dist: google-auth-oauthlib>=1.0.0
Requires-Dist: google-cloud-translate>=3.11.0
Requires-Dist: igraph
Requires-Dist: instructor
Requires-Dist: jsonlines
Requires-Dist: jsonschema
Requires-Dist: markdown
Requires-Dist: markdown3-newtab
Requires-Dist: more-itertools
Requires-Dist: networkx
Requires-Dist: nltk
Requires-Dist: numpy<3.0.0,>=2.3.0
Requires-Dist: openai<2.0.0,>=1.0.0
Requires-Dist: openpyxl
Requires-Dist: pandas<3.0.0,>=2.0.0
Requires-Dist: plotly
Requires-Dist: psycopg2-binary
Requires-Dist: pysocks
Requires-Dist: pyyaml
Requires-Dist: regex
Requires-Dist: requests
Requires-Dist: requests-cache
Requires-Dist: scikit-learn<2.0.0,>=1.7.0
Requires-Dist: scikit-network
Requires-Dist: scipy<2.0.0,>=1.11.0
Requires-Dist: selenium<5.0.0,>=4.15.0
Requires-Dist: sqlalchemy-utils
Requires-Dist: sqlalchemy<3.0.0,>=2.0.0
Requires-Dist: tiktoken
Requires-Dist: torch<3.0.0,>=2.0.0
Requires-Dist: transformers<5.0.0,>=4.35.0
Requires-Dist: treelib
Requires-Dist: umap
Requires-Dist: unstructured[all-docs]<1.0.0,>=0.16.12
Requires-Dist: url-normalize
Requires-Dist: webdriver-manager
Requires-Dist: wikipedia-api
Requires-Dist: xlsxwriter
Provides-Extra: docs
Requires-Dist: mkdocs-material>=9.0.0; extra == 'docs'
Requires-Dist: mkdocs>=1.5.0; extra == 'docs'
Provides-Extra: lint
Requires-Dist: black>=23.0.0; extra == 'lint'
Requires-Dist: mypy>=1.0.0; extra == 'lint'
Requires-Dist: ruff>=0.1.0; extra == 'lint'
Provides-Extra: test
Requires-Dist: pytest-cov>=4.0.0; extra == 'test'
Requires-Dist: pytest-mock>=3.12.0; extra == 'test'
Requires-Dist: pytest>=7.0.0; extra == 'test'
